event_manager_lib/__init__.py
event_manager_lib/enum.py
event_manager_lib/manager.py
event_manager_lib-0.1.0.dist-info/WHEEL
event_manager_lib-0.1.0.dist-info/METADATA
event_manager_lib-0.1.0.dist-info/RECORD
