Metadata-Version: 2.1
Name: event-manager-lib
Version: 0.1.0
Summary: Event/ State Manager library/ SDK
Author: David Lubomirov
Author-email: davidlubomirov@gmail.com
Requires-Python: >=3.8.0,<3.9.0
Classifier: Programming Language :: Python :: 3
Classifier: Programming Language :: Python :: 3.8
